sankeyflow/__init__.py
sankeyflow/sankeyflow.py
sankeyflow-0.4.1.dist-info/LICENSE
sankeyflow-0.4.1.dist-info/METADATA
sankeyflow-0.4.1.dist-info/WHEEL
sankeyflow-0.4.1.dist-info/top_level.txt
sankeyflow-0.4.1.dist-info/RECORD
