Metadata-Version: 2.1
Name: sankeyflow
Version: 0.4.1
Summary: Creating Sankey flow diagrams in Matplotlib
Home-page: https://github.com/riley-x/SankeyFlow
Author: Riley Xu
Author-email: riley.xu@gmail.com
Project-URL: Bug Tracker, https://github.com/riley-x/SankeyFlow/issues
Classifier: Programming Language :: Python :: 3
Classifier: License :: OSI Approved :: BSD License
Classifier: Operating System :: OS Independent
Requires-Python: >=3.8
License-File: LICENSE
